atom/__init__.py
atom/views.py
atom/templates/atom_navlink.html
atom/templates/feed.xml
atom/templates/index.html
flaskbb_plugin_atom-0.2.0.dist-info/LICENSE
flaskbb_plugin_atom-0.2.0.dist-info/METADATA
flaskbb_plugin_atom-0.2.0.dist-info/WHEEL
flaskbb_plugin_atom-0.2.0.dist-info/entry_points.txt
flaskbb_plugin_atom-0.2.0.dist-info/top_level.txt
flaskbb_plugin_atom-0.2.0.dist-info/RECORD
